galaxypad/__init__.py
galaxypad/__main__.py
galaxypad/pad.py
galaxypad-1.0.4.dist-info/METADATA
galaxypad-1.0.4.dist-info/WHEEL
galaxypad-1.0.4.dist-info/entry_points.txt
galaxypad-1.0.4.dist-info/top_level.txt
galaxypad-1.0.4.dist-info/RECORD
