Metadata-Version: 2.1
Name: galaxypad
Version: 1.0.4
Summary: Python tool to record PAD playback for Super Mario Galaxy 2
Home-page: https://github.com/SunakazeKun/galaxypad
Author: Aurum
License: gpl-3.0
Keywords: nintendo,super-mario-galaxy-2,pad,dolphin,modding
Classifier: Intended Audience :: Developers
Classifier: Topic :: Software Development :: Libraries
Classifier: License :: OSI Approved :: GNU General Public License v3 (GPLv3)
Classifier: Programming Language :: Python :: 3 :: Only
Requires-Python: >=3.10
Requires-Dist: dolphin-memory-engine
